SpiritLong_database/__init__.py
SpiritLong_database/database_SQLite.py
SpiritLong_database/database_mysql.py
SpiritLong_email/__init__.py
SpiritLong_email/email.py
SpiritLong_excel/__init__.py
SpiritLong_excel/excel.py
SpiritLong_utility/__init__.py
SpiritLong_utility/utility_SSH.py
SpiritLong_utility/utility_copyright.py
SpiritLong_utility/utility_datetime.py
SpiritLong_utility/utility_files.py
SpiritLong_utility/utility_math.py
SpiritLong_utility/utility_string.py
SpiritLong_webframe/__init__.py
SpiritLong_webframe/webframe_SpringBoot.py
SpiritLong_webframe/webframe_SpringBoot_pom_xml.py
SpiritLong_webframe/webframe_VUE3.py
SpiritLong_webframe/webframe_VUE3_App_vue.py
SpiritLong_webframe/webframe_VUE3_webframe_js.py
SpiritLong_webframe/webframe_postman.py
SpiritLong_webframe/webframe_python.py
SpiritLong_webframe/webframe_python_routes_py.py
SpiritLong_webframe/webframe_python_webframe_py.py
SpiritLong_word/__init__.py
SpiritLong_word/word.py
spiritlong-0.0.101.dist-info/licenses/LICENSE.txt
spiritlong-0.0.101.dist-info/METADATA
spiritlong-0.0.101.dist-info/WHEEL
spiritlong-0.0.101.dist-info/top_level.txt
spiritlong-0.0.101.dist-info/RECORD
