Metadata-Version: 2.4
Name: spiritlong
Version: 0.0.101
Summary: SpiritLong python tool package from pip
Home-page: https://spiritlong-exon.com/pip
Author: SpiritLong
Author-email: arthuryang@spiritlong.com
Maintainer: SpiritLong
Maintainer-email: shun@spiritlong.com
Classifier: Development Status :: 3 - Alpha
Classifier: Programming Language :: Python :: 3
Classifier: Intended Audience :: Developers
Classifier: Operating System :: OS Independent
Requires-Python: >=3.7
License-File: LICENSE.txt
Requires-Dist: openpyxl
Requires-Dist: mysqlclient
Requires-Dist: wechatpy
Requires-Dist: dbutils
Requires-Dist: python-docx
Requires-Dist: redis
Requires-Dist: chardet
Requires-Dist: xlwings
Requires-Dist: chardet
Dynamic: author
Dynamic: author-email
Dynamic: classifier
Dynamic: description
Dynamic: description-content-type
Dynamic: home-page
Dynamic: license-file
Dynamic: maintainer
Dynamic: maintainer-email
Dynamic: requires-dist
Dynamic: requires-python
Dynamic: summary
